{
  "sources": [
    {
      "source": "discord",
      "sourceId": "codaqui",
      "guildId": "829882821559451659",
      "label": "Discord Codaqui",
      "emoji": "💬",
      "description": "Eventos e encontros da comunidade hospedados no servidor da Codaqui.",
      "ctaLabel": "Entrar no Discord da Codaqui",
      "ctaHref": "https://discord.com/invite/xuTtxqCPpz",
      "widgetUrl": "https://discord.com/api/guilds/829882821559451659/widget.json",
      "defaultHost": "Comunidade Codaqui",
      "defaultLocation": "Servidor da Codaqui no Discord",
      "defaultPlatform": "Discord"
    },
    {
      "source": "meetup",
      "sourceId": "devparana",
      "urlname": "developerparana",
      "locale": "pt-BR",
      "label": "Dev Paraná no Meetup",
      "emoji": "📍",
      "description": "Eventos publicados pelo Dev Paraná no Meetup, incluindo histórico e próximos encontros.",
      "ctaLabel": "Abrir grupo do Dev Paraná",
      "ctaHref": "https://www.meetup.com/pt-BR/developerparana/",
      "defaultHost": "Dev Paraná",
      "defaultLocation": "Meetup",
      "defaultPlatform": "Meetup",
      "fallbackEvents": []
    },
    {
      "source": "ocgroups",
      "sourceId": "cloud-native-maringa",
      "groupId": "sq5vsqs",
      "label": "Cloud Native Maringá",
      "emoji": "☁️",
      "description": "Eventos do chapter oficial CNCF em Maringá — Kubernetes, containers, cloud-native e SRE.",
      "ctaLabel": "Ver no CNCF Open Community Groups",
      "ctaHref": "https://ocgroups.dev/cncf/group/sq5vsqs",
      "defaultHost": "Cloud Native Maringá",
      "defaultLocation": "Maringá, PR",
      "defaultPlatform": "CNCF Open Community Groups",
      "timezone": "America/Sao_Paulo",
      "fallbackEvents": []
    }
  ]
}
