{
  "generatedAt": "2026-04-02T03:57:56.686Z",
  "source": {
    "source": "meetup",
    "sourceId": "devparana",
    "type": "meetup",
    "label": "Dev Paraná no Meetup",
    "emoji": "📍",
    "description": "Eventos publicados pelo Dev Paraná no Meetup, incluindo histórico e próximos encontros.",
    "ctaLabel": "Abrir grupo do Dev Paraná",
    "ctaHref": "https://www.meetup.com/pt-BR/developerparana/",
    "refreshStrategy": "Workflow periodico consulta a API da fonte, gera um indice leve para a UI e salva um arquivo por evento para detalhe e cache.",
    "generatedAt": "2026-04-02T03:57:56.686Z"
  },
  "event": {
    "id": "261173730",
    "title": "2º  Delphi Ingá - DB1",
    "summary": "Devida as políticas do local, necessitamos que você informe a DB1 algumas informações nesse link: https://w3l.page.link/ymsQeVVZHibWWX8h6 Vamos falar de Delphi? Sobre o local: - Segue os padrões de acessibilidade em tod…",
    "startAt": "2019-05-21T19:00:00-03:00",
    "endAt": "2019-05-21T21:00:00-03:00",
    "timezone": "America/Sao_Paulo",
    "platform": "Meetup",
    "host": "Dev Paraná",
    "location": "DB1 Global Software · Avenida Advogado Horácio Raccanello Filho · Maringá",
    "href": "https://www.meetup.com/developerparana/events/261173730/",
    "tags": [
      "meetup",
      "devparana",
      "presencial"
    ],
    "ctaLabel": "Ver evento no Meetup",
    "featured": false,
    "status": "completed",
    "entityType": "external",
    "userCount": 23,
    "creatorName": "Marcos Florencio",
    "creatorId": "188007973",
    "imageUrl": "https://secure.meetupstatic.com/photos/event/c/9/f/7/highres_481371703.jpeg"
  }
}
