{
  "generatedAt": "2026-04-07T05:35:16.007Z",
  "source": {
    "source": "meetup",
    "sourceId": "devparana",
    "type": "meetup",
    "label": "Dev Paraná no Meetup",
    "emoji": "📍",
    "description": "Eventos publicados pelo Dev Paraná no Meetup, incluindo histórico e próximos encontros.",
    "ctaLabel": "Abrir grupo do Dev Paraná",
    "ctaHref": "https://www.meetup.com/pt-BR/developerparana/",
    "refreshStrategy": "Workflow periodico consulta a API da fonte, gera um indice leve para a UI e salva um arquivo por evento para detalhe e cache.",
    "generatedAt": "2026-04-07T05:35:16.007Z"
  },
  "event": {
    "id": "276811488",
    "title": "#20 Maringá Agile - Lean Coffee",
    "summary": "LINK : https://meet.google.com/apo-orci-pkx A primeira edição do ano, será em um formato Lean Coffe, onde será abordado os assuntos que mais interessam o grupo para serem discutidos. Lembrando, \"Lean Coffee\" é um evento…",
    "startAt": "2021-03-17T19:00:00-03:00",
    "endAt": "2021-03-17T21:00:00-03:00",
    "timezone": "America/Sao_Paulo",
    "platform": "Meetup",
    "host": "Dev Paraná",
    "location": "Online via Meetup",
    "href": "https://www.meetup.com/developerparana/events/276811488/",
    "tags": [
      "meetup",
      "devparana",
      "online"
    ],
    "ctaLabel": "Ver evento no Meetup",
    "featured": false,
    "status": "completed",
    "entityType": "external",
    "userCount": 31,
    "creatorName": "Kelly Garcia",
    "creatorId": "249252072",
    "imageUrl": "https://secure.meetupstatic.com/photos/event/d/2/6/4/highres_490673860.jpeg"
  }
}
